__init__.py
monaco_race_report-0.0.2.dist-info/licenses/LICENSE
race_report/__init__.py
race_report/cli.py
race_report/parse_and_report.py
monaco_race_report-0.0.2.dist-info/METADATA
monaco_race_report-0.0.2.dist-info/WHEEL
monaco_race_report-0.0.2.dist-info/entry_points.txt
monaco_race_report-0.0.2.dist-info/top_level.txt
monaco_race_report-0.0.2.dist-info/RECORD
