Metadata-Version: 2.4
Name: monaco-race-report
Version: 0.0.2
Summary: Package for parcing F1 race data files and building and printing a report either for
Author-email: Andrii Bezus <silverbird5567@gmail.com>
License-Expression: MIT
Classifier: Programming Language :: Python :: 3
Classifier: Operating System :: OS Independent
Requires-Python: >=3.8
License-File: LICENSE
Dynamic: license-file
